odoo/addons/event_registration_partner_unique/README.rst
odoo/addons/event_registration_partner_unique/__init__.py
odoo/addons/event_registration_partner_unique/__manifest__.py
odoo/addons/event_registration_partner_unique/i18n/es.po
odoo/addons/event_registration_partner_unique/i18n/event_registration_partner_unique.pot
odoo/addons/event_registration_partner_unique/models/__init__.py
odoo/addons/event_registration_partner_unique/models/event.py
odoo/addons/event_registration_partner_unique/readme/CONTRIBUTORS.rst
odoo/addons/event_registration_partner_unique/readme/DESCRIPTION.rst
odoo/addons/event_registration_partner_unique/readme/ROADMAP.rst
odoo/addons/event_registration_partner_unique/readme/USAGE.rst
odoo/addons/event_registration_partner_unique/static/description/icon.png
odoo/addons/event_registration_partner_unique/static/description/index.html
odoo/addons/event_registration_partner_unique/tests/__init__.py
odoo/addons/event_registration_partner_unique/tests/test_event.py
odoo/addons/event_registration_partner_unique/views/event_event_view.xml
odoo14_addon_event_registration_partner_unique-14.0.1.0.1.dist-info/METADATA
odoo14_addon_event_registration_partner_unique-14.0.1.0.1.dist-info/WHEEL
odoo14_addon_event_registration_partner_unique-14.0.1.0.1.dist-info/top_level.txt
odoo14_addon_event_registration_partner_unique-14.0.1.0.1.dist-info/RECORD
