Metadata-Version: 2.1
Name: odoo14-addon-event-registration-partner-unique
Version: 14.0.1.0.1
Summary: Enforces 1 registration per partner and event
Home-page: https://github.com/OCA/event
Author: Tecnativa, Odoo Community Association (OCA)
Author-email: support@odoo-community.org
License: AGPL-3
Platform: UNKNOWN
Classifier: Programming Language :: Python
Classifier: Framework :: Odoo
Classifier: Framework :: Odoo :: 14.0
Classifier: License :: OSI Approved :: GNU Affero General Public License v3
Requires-Python: >=3.6
Requires-Dist: odoo14-addon-partner-event
Requires-Dist: odoo (<14.1dev,>=14.0a)
